TuijianXitongYushangShenduXuexi121/README.md
TuijianXitongYushangShenduXuexi121/__init__.py
TuijianXitongYushangShenduXuexi121/__main__.py
TuijianXitongYushangShenduXuexi121/file.epub
TuijianXitongYushangShenduXuexi121/index.html
TuijianXitongYushangShenduXuexi121/css/__init__.py
TuijianXitongYushangShenduXuexi121/css/annotations.css
TuijianXitongYushangShenduXuexi121/css/main.css
TuijianXitongYushangShenduXuexi121/css/normalize.css
TuijianXitongYushangShenduXuexi121/css/popup.css
TuijianXitongYushangShenduXuexi121/font/__init__.py
TuijianXitongYushangShenduXuexi121/font/fontello.eot
TuijianXitongYushangShenduXuexi121/font/fontello.svg
TuijianXitongYushangShenduXuexi121/font/fontello.ttf
TuijianXitongYushangShenduXuexi121/font/fontello.woff
TuijianXitongYushangShenduXuexi121/img/__init__.py
TuijianXitongYushangShenduXuexi121/img/annotator-glyph-sprite.png
TuijianXitongYushangShenduXuexi121/img/annotator-icon-sprite.png
TuijianXitongYushangShenduXuexi121/img/apple-touch-icon.png
TuijianXitongYushangShenduXuexi121/img/cancelfullscreen.png
TuijianXitongYushangShenduXuexi121/img/close.png
TuijianXitongYushangShenduXuexi121/img/fullscreen.png
TuijianXitongYushangShenduXuexi121/img/loader.gif
TuijianXitongYushangShenduXuexi121/img/menu-icon.png
TuijianXitongYushangShenduXuexi121/img/save.png
TuijianXitongYushangShenduXuexi121/img/saved.png
TuijianXitongYushangShenduXuexi121/img/settings-s.png
TuijianXitongYushangShenduXuexi121/img/settings.png
TuijianXitongYushangShenduXuexi121/img/star.png
TuijianXitongYushangShenduXuexi121/js/__init__.py
TuijianXitongYushangShenduXuexi121/js/epub.js
TuijianXitongYushangShenduXuexi121/js/epub.min.js
TuijianXitongYushangShenduXuexi121/js/epub.min.map
TuijianXitongYushangShenduXuexi121/js/hooks.min.js
TuijianXitongYushangShenduXuexi121/js/hooks.min.map
TuijianXitongYushangShenduXuexi121/js/reader.js
TuijianXitongYushangShenduXuexi121/js/reader.js.map
TuijianXitongYushangShenduXuexi121/js/reader.min.js
tuijian_xitong_yushang_shendu_xuexi_1_21-2024.3.3.0.dist-info/METADATA
tuijian_xitong_yushang_shendu_xuexi_1_21-2024.3.3.0.dist-info/WHEEL
tuijian_xitong_yushang_shendu_xuexi_1_21-2024.3.3.0.dist-info/entry_points.txt
tuijian_xitong_yushang_shendu_xuexi_1_21-2024.3.3.0.dist-info/top_level.txt
tuijian_xitong_yushang_shendu_xuexi_1_21-2024.3.3.0.dist-info/RECORD
